firm_client-1.0.0.dist-info/METADATA
firm_client-1.0.0.dist-info/WHEEL
firm_client-1.0.0.dist-info/licenses/LICENSE
firm_client/__init__.py
firm_client/firm_client.cp311-win_amd64.pyd
firm_python/firm_client.pyi
firm_client-1.0.0.dist-info/RECORD
