Metadata-Version: 2.4
Name: firm-client
Version: 1.0.0
Classifier: Development Status :: 4 - Beta
Classifier: Programming Language :: Python :: 3.10
Classifier: Programming Language :: Python :: 3.11
Classifier: Programming Language :: Python :: 3.12
Classifier: Programming Language :: Python :: 3.13
Classifier: Programming Language :: Python :: 3.14
Classifier: License :: OSI Approved :: MIT License
Classifier: Programming Language :: Rust
License-File: LICENSE
Summary: Python bindings for FIRM Client using Rust
License-Expression: MIT
Requires-Python: >=3.10
Project-URL: Homepage, https://ncsurocketry.org
Project-URL: Source, https://github.com/NCSU-High-Powered-Rocketry-Club/FIRM-Client
